Metadata-Version: 2.1
Name: sts-zap
Version: 0.0
Summary: sts_zap
Author-email: ilapronin0700@gmail.com
